LICENSE
MANIFEST.in
README.md
requirements.txt
setup.py
ironsource_api/__init__.py
ironsource_api/base_api.py
ironsource_api/ironsource_api.py
ironsource_api/utils.py
ironsource_api/monetize_api/__init__.py
ironsource_api/monetize_api/instance_config.py
ironsource_api/monetize_api/mediation_group_priority.py
ironsource_api/monetize_api/monetize_api.py
ironsource_api/monetize_api/placement_config.py
ironsource_api/promote_api/__init__.py
ironsource_api/promote_api/audience_list.py
ironsource_api/promote_api/campaign_bids.py
ironsource_api/promote_api/creatives.py
ironsource_api/promote_api/promote_api.py
ironsource_mobile_api.egg-info/PKG-INFO
ironsource_mobile_api.egg-info/SOURCES.txt
ironsource_mobile_api.egg-info/dependency_links.txt
ironsource_mobile_api.egg-info/requires.txt
ironsource_mobile_api.egg-info/top_level.txt