Metadata-Version: 2.1
Name: ironsource-mobile-api
Version: 1.1.0
Home-page: https://github.com/ironSource/mobile-api-lib-python
Author: IronSource Ltd.
Author-email: mobile-api-lib-ci@is.com
License: Apache-2.0
Requires-Python: >=3.7
License-File: LICENSE
